{
  "code": 200,
  "currentTime": 1494882994251,
  "data": {
    "entry": {
      "arrivalsAndDepartures": [
        {
          "arrivalEnabled": true,
          "blockTripSequence": 16,
          "departureEnabled": true,
          "distanceFromStop": 377.99670101230004,
          "frequency": null,
          "lastUpdateTime": 0,
          "numberOfStopsAway": 0,
          "predicted": false,
          "predictedArrivalInterval": null,
          "predictedArrivalTime": 0,
          "predictedDepartureInterval": null,
          "predictedDepartureTime": 0,
          "routeId": "1_100227",
          "routeLongName": "",
          "routeShortName": "47",
          "scheduledArrivalInterval": null,
          "scheduledArrivalTime": 1494865725000,
          "scheduledDepartureInterval": null,
          "scheduledDepartureTime": 1494865725000,
          "serviceDate": 1494831600000,
          "situationIds": [],
          "status": "default",
          "stopId": "1_11130",
          "stopSequence": 4,
          "totalStopsInTrip": 11,
          "tripHeadsign": "Summit Via Pike St",
          "tripId": "1_33488936",
          "tripStatus": {
            "activeTripId": "1_33488936",
            "blockTripSequence": 16,
            "closestStop": "1_1180",
            "closestStopTimeOffset": -36,
            "distanceAlongTrip": 0,
            "frequency": null,
            "lastKnownDistanceAlongTrip": 0,
            "lastKnownLocation": null,
            "lastKnownOrientation": 0,
            "lastLocationUpdateTime": 0,
            "lastUpdateTime": 0,
            "nextStop": "1_11130",
            "nextStopTimeOffset": 131,
            "orientation": 22.64209271608629,
            "phase": "",
            "position": {
              "lat": 47.610686158837375,
              "lon": -122.33556423492699
            },
            "predicted": false,
            "scheduleDeviation": 0,
            "scheduledDistanceAlongTrip": 1111.4206319382429,
            "serviceDate": 1494831600000,
            "situationIds": [],
            "status": "default",
            "totalDistanceAlongTrip": 3471.835924447578,
            "vehicleId": ""
          },
          "vehicleId": ""
        },
        {
          "arrivalEnabled": true,
          "blockTripSequence": 7,
          "departureEnabled": true,
          "distanceFromStop": 778.137468461995,
          "frequency": null,
          "lastUpdateTime": 0,
          "numberOfStopsAway": 1,
          "predicted": false,
          "predictedArrivalInterval": null,
          "predictedArrivalTime": 0,
          "predictedDepartureInterval": null,
          "predictedDepartureTime": 0,
          "routeId": "1_100002",
          "routeLongName": "",
          "routeShortName": "10",
          "scheduledArrivalInterval": null,
          "scheduledArrivalTime": 1494865872000,
          "scheduledDepartureInterval": null,
          "scheduledDepartureTime": 1494865872000,
          "serviceDate": 1494831600000,
          "situationIds": [],
          "status": "default",
          "stopId": "1_11130",
          "stopSequence": 4,
          "totalStopsInTrip": 19,
          "tripHeadsign": "Capitol Hill Via 15th Ave E",
          "tripId": "1_33489847",
          "tripStatus": {
            "activeTripId": "1_33489847",
            "blockTripSequence": 7,
            "closestStop": "1_1120",
            "closestStopTimeOffset": -91,
            "distanceAlongTrip": 0,
            "frequency": null,
            "lastKnownDistanceAlongTrip": 0,
            "lastKnownLocation": null,
            "lastKnownOrientation": 0,
            "lastLocationUpdateTime": 0,
            "lastUpdateTime": 0,
            "nextStop": "1_1180",
            "nextStopTimeOffset": 144,
            "orientation": 312.1014232007454,
            "phase": "",
            "position": {
              "lat": 47.61008510451313,
              "lon": -122.33963779323476
            },
            "predicted": false,
            "scheduleDeviation": 0,
            "scheduledDistanceAlongTrip": 711.2798644885443,
            "serviceDate": 1494831600000,
            "situationIds": [],
            "status": "default",
            "totalDistanceAlongTrip": 5291.517013465226,
            "vehicleId": ""
          },
          "vehicleId": ""
        },
        {
          "arrivalEnabled": true,
          "blockTripSequence": 11,
          "departureEnabled": true,
          "distanceFromStop": 2713.7500051448005,
          "frequency": null,
          "lastUpdateTime": 0,
          "numberOfStopsAway": 8,
          "predicted": false,
          "predictedArrivalInterval": null,
          "predictedArrivalTime": 0,
          "predictedDepartureInterval": null,
          "predictedDepartureTime": 0,
          "routeId": "1_100002",
          "routeLongName": "",
          "routeShortName": "10",
          "scheduledArrivalInterval": null,
          "scheduledArrivalTime": 1494866532000,
          "scheduledDepartureInterval": null,
          "scheduledDepartureTime": 1494866532000,
          "serviceDate": 1494831600000,
          "situationIds": [],
          "status": "default",
          "stopId": "1_11130",
          "stopSequence": 4,
          "totalStopsInTrip": 19,
          "tripHeadsign": "Capitol Hill Via 15th Ave E",
          "tripId": "1_33489764",
          "tripStatus": {
            "activeTripId": "1_33489763",
            "blockTripSequence": 10,
            "closestStop": "1_29264",
            "closestStopTimeOffset": -25,
            "distanceAlongTrip": 0,
            "frequency": null,
            "lastKnownDistanceAlongTrip": 0,
            "lastKnownLocation": null,
            "lastKnownOrientation": 0,
            "lastLocationUpdateTime": 0,
            "lastUpdateTime": 0,
            "nextStop": "1_29266",
            "nextStopTimeOffset": 63,
            "orientation": 180.81265159437206,
            "phase": "",
            "position": {
              "lat": 47.61989629868377,
              "lon": -122.32246594279448
            },
            "predicted": false,
            "scheduleDeviation": 0,
            "scheduledDistanceAlongTrip": 2111.5551527951757,
            "serviceDate": 1494831600000,
            "situationIds": [],
            "status": "default",
            "totalDistanceAlongTrip": 3291.0269005055384,
            "vehicleId": ""
          },
          "vehicleId": ""
        },
        {
          "arrivalEnabled": true,
          "blockTripSequence": 7,
          "departureEnabled": true,
          "distanceFromStop": 4838.053800511749,
          "frequency": null,
          "lastUpdateTime": 0,
          "numberOfStopsAway": 18,
          "predicted": false,
          "predictedArrivalInterval": null,
          "predictedArrivalTime": 0,
          "predictedDepartureInterval": null,
          "predictedDepartureTime": 0,
          "routeId": "1_100002",
          "routeLongName": "",
          "routeShortName": "10",
          "scheduledArrivalInterval": null,
          "scheduledArrivalTime": 1494867432000,
          "scheduledDepartureInterval": null,
          "scheduledDepartureTime": 1494867432000,
          "serviceDate": 1494831600000,
          "situationIds": [],
          "status": "default",
          "stopId": "1_11130",
          "stopSequence": 4,
          "totalStopsInTrip": 19,
          "tripHeadsign": "Capitol Hill Via 15th Ave E",
          "tripId": "1_33489871",
          "tripStatus": {
            "activeTripId": "1_33489869",
            "blockTripSequence": 5,
            "closestStop": "1_11370",
            "closestStopTimeOffset": 0,
            "distanceAlongTrip": 0,
            "frequency": null,
            "lastKnownDistanceAlongTrip": 0,
            "lastKnownLocation": null,
            "lastKnownOrientation": 0,
            "lastLocationUpdateTime": 0,
            "lastUpdateTime": 0,
            "nextStop": "1_11370",
            "nextStopTimeOffset": 0,
            "orientation": 269.37406955377463,
            "phase": "",
            "position": {
              "lat": 47.6323896510995,
              "lon": -122.31249199288676
            },
            "predicted": false,
            "scheduleDeviation": 0,
            "scheduledDistanceAlongTrip": 5285.106491661227,
            "serviceDate": 1494831600000,
            "situationIds": [],
            "status": "default",
            "totalDistanceAlongTrip": 5291.517013465226,
            "vehicleId": ""
          },
          "vehicleId": ""
        }
      ],
      "nearbyStopIds": [],
      "situationIds": [],
      "stopId": "1_11130"
    },
    "references": {
      "agencies": [
        {
          "disclaimer": "",
          "email": "",
          "fareUrl": "",
          "id": "1",
          "lang": "EN",
          "name": "Metro Transit",
          "phone": "206-553-3000",
          "privateService": false,
          "timezone": "America/Los_Angeles",
          "url": "http://metro.kingcounty.gov"
        },
        {
          "disclaimer": "",
          "email": "",
          "fareUrl": "",
          "id": "40",
          "lang": "EN",
          "name": "Sound Transit",
          "phone": "1-888-889-6368",
          "privateService": false,
          "timezone": "America/Los_Angeles",
          "url": "http://www.soundtransit.org"
        }
      ],
      "routes": [
        {
          "agencyId": "1",
          "color": "",
          "description": "Capitol Hill - Downtown Seattle",
          "id": "1_100002",
          "longName": "",
          "shortName": "10",
          "textColor": "",
          "type": 3,
          "url": "http://metro.kingcounty.gov/schedules/010/n0.html"
        },
        {
          "agencyId": "1",
          "color": "",
          "description": "U Dist - Montlake - Capitol Hill - Downtown",
          "id": "1_100223",
          "longName": "",
          "shortName": "43",
          "textColor": "",
          "type": 3,
          "url": "http://metro.kingcounty.gov/schedules/043/n0.html"
        },
        {
          "agencyId": "1",
          "color": "",
          "description": "Summit - Downtown Seattle",
          "id": "1_100227",
          "longName": "",
          "shortName": "47",
          "textColor": "",
          "type": 3,
          "url": "http://metro.kingcounty.gov/schedules/047/n0.html"
        },
        {
          "agencyId": "1",
          "color": "",
          "description": "Downtown Seattle to Madison Park to Madrona",
          "id": "1_100279",
          "longName": "",
          "shortName": "84",
          "textColor": "",
          "type": 3,
          "url": "http://metro.kingcounty.gov/schedules/084/n0.html"
        },
        {
          "agencyId": "1",
          "color": "",
          "description": "Madison Park to Capitol Hill to Downtown Seattle",
          "id": "1_100009",
          "longName": "",
          "shortName": "11",
          "textColor": "",
          "type": 3,
          "url": "http://metro.kingcounty.gov/schedules/011/n0.html"
        },
        {
          "agencyId": "1",
          "color": "",
          "description": "U Dist - Broadway - Downtown Sea",
          "id": "1_100447",
          "longName": "",
          "shortName": "49",
          "textColor": "",
          "type": 3,
          "url": "http://metro.kingcounty.gov/schedules/049/n0.html"
        },
        {
          "agencyId": "1",
          "color": "",
          "description": "Black Diamond to Downtown Seattle",
          "id": "1_100041",
          "longName": "",
          "shortName": "143",
          "textColor": "",
          "type": 3,
          "url": "http://metro.kingcounty.gov/schedules/143/n0.html"
        },
        {
          "agencyId": "1",
          "color": "",
          "description": "Lake Meridian P&R to Downtown Seattle",
          "id": "1_100475",
          "longName": "",
          "shortName": "157",
          "textColor": "",
          "type": 3,
          "url": "http://metro.kingcounty.gov/schedules/157/n0.html"
        },
        {
          "agencyId": "1",
          "color": "",
          "description": "Kent East Hill to Downtown Seattle",
          "id": "1_100051",
          "longName": "",
          "shortName": "158",
          "textColor": "",
          "type": 3,
          "url": "http://metro.kingcounty.gov/schedules/158/n0.html"
        },
        {
          "agencyId": "1",
          "color": "",
          "description": "Timberlane/Lake Mer P&R/Kent Rail Sta/DT Seattle",
          "id": "1_100052",
          "longName": "",
          "shortName": "159",
          "textColor": "",
          "type": 3,
          "url": "http://metro.kingcounty.gov/schedules/159/n0.html"
        },
        {
          "agencyId": "1",
          "color": "",
          "description": "Twin Lakes P&R to Downtown Seattle",
          "id": "1_100070",
          "longName": "",
          "shortName": "179",
          "textColor": "",
          "type": 3,
          "url": "http://metro.kingcounty.gov/schedules/179/n0.html"
        },
        {
          "agencyId": "1",
          "color": "",
          "description": "Star Lake to Downtown Seattle",
          "id": "1_100084",
          "longName": "",
          "shortName": "192",
          "textColor": "",
          "type": 3,
          "url": "http://metro.kingcounty.gov/schedules/192/n0.html"
        },
        {
          "agencyId": "1",
          "color": "",
          "description": "Bear Creek P&R to Sammamish to Downtown Seattle",
          "id": "1_100108",
          "longName": "",
          "shortName": "216",
          "textColor": "",
          "type": 3,
          "url": "http://metro.kingcounty.gov/schedules/216/n0.html"
        },
        {
          "agencyId": "1",
          "color": "",
          "description": "Issaquah Hlnds Downtown",
          "id": "1_100459",
          "longName": "",
          "shortName": "218",
          "textColor": "",
          "type": 3,
          "url": "http://metro.kingcounty.gov/schedules/218/n0.html"
        },
        {
          "agencyId": "1",
          "color": "",
          "description": "Redmond  Issaquah Highlands P&R  Downtown Seattle",
          "id": "1_100110",
          "longName": "",
          "shortName": "219",
          "textColor": "",
          "type": 3,
          "url": "http://metro.kingcounty.gov/schedules/219/n0.html"
        },
        {
          "agencyId": "40",
          "color": "",
          "description": "",
          "id": "40_577",
          "longName": "Federal Way - Seattle",
          "shortName": "577",
          "textColor": "",
          "type": 3,
          "url": ""
        },
        {
          "agencyId": "1",
          "color": "",
          "description": "Seattle Center to Capitol Hill to Rainier Beach",
          "id": "1_100275",
          "longName": "",
          "shortName": "8",
          "textColor": "",
          "type": 3,
          "url": "http://metro.kingcounty.gov/schedules/008/n0.html"
        }
      ],
      "situations": [],
      "stops": [
        {
          "code": "11130",
          "direction": "NE",
          "id": "1_11130",
          "lat": 47.612415,
          "locationType": 0,
          "lon": -122.331223,
          "name": "Pike St & Convention Pl",
          "routeIds": [
            "1_100002",
            "1_100223",
            "1_100227",
            "1_100279"
          ],
          "wheelchairBoarding": "UNKNOWN"
        },
        {
          "code": "1180",
          "direction": "NE",
          "id": "1_1180",
          "lat": 47.610134,
          "locationType": 0,
          "lon": -122.336685,
          "name": "Pike St & 4th Ave",
          "routeIds": [
            "1_100002",
            "1_100009",
            "1_100223",
            "1_100227",
            "1_100447",
            "1_100279"
          ],
          "wheelchairBoarding": "UNKNOWN"
        },
        {
          "code": "1120",
          "direction": "W",
          "id": "1_1120",
          "lat": 47.611103,
          "locationType": 0,
          "lon": -122.338028,
          "name": "Pine St & 4th Ave",
          "routeIds": [
            "1_100002",
            "1_100009",
            "1_100227",
            "1_100447",
            "1_100041",
            "1_100475",
            "1_100051",
            "1_100052",
            "1_100070",
            "1_100084",
            "1_100108",
            "1_100459",
            "1_100110",
            "40_577"
          ],
          "wheelchairBoarding": "UNKNOWN"
        },
        {
          "code": "29264",
          "direction": "W",
          "id": "1_29264",
          "lat": 47.619972,
          "locationType": 0,
          "lon": -122.321304,
          "name": "E Olive Way & Broadway  E",
          "routeIds": [
            "1_100275",
            "1_100002",
            "1_100223"
          ],
          "wheelchairBoarding": "UNKNOWN"
        },
        {
          "code": "29266",
          "direction": "SW",
          "id": "1_29266",
          "lat": 47.619152,
          "locationType": 0,
          "lon": -122.325119,
          "name": "E Olive Way & Summit Ave E",
          "routeIds": [
            "1_100275",
            "1_100002",
            "1_100223"
          ],
          "wheelchairBoarding": "UNKNOWN"
        },
        {
          "code": "11370",
          "direction": "S",
          "id": "1_11370",
          "lat": 47.632389,
          "locationType": 0,
          "lon": -122.312607,
          "name": "15th Ave E & E Galer St",
          "routeIds": [
            "1_100002"
          ],
          "wheelchairBoarding": "UNKNOWN"
        }
      ],
      "trips": [
        {
          "blockId": "1_4475868",
          "directionId": "0",
          "id": "1_33488936",
          "routeId": "1_100227",
          "routeShortName": "",
          "serviceId": "1_110802",
          "shapeId": "1_11047005",
          "timeZone": "",
          "tripHeadsign": "Summit Via Pike St",
          "tripShortName": "LOCAL"
        },
        {
          "blockId": "1_4475928",
          "directionId": "0",
          "id": "1_33489847",
          "routeId": "1_100002",
          "routeShortName": "",
          "serviceId": "1_110802",
          "shapeId": "1_11010033",
          "timeZone": "",
          "tripHeadsign": "Capitol Hill Via 15th Ave E",
          "tripShortName": "LOCAL"
        },
        {
          "blockId": "1_4475924",
          "directionId": "0",
          "id": "1_33489764",
          "routeId": "1_100002",
          "routeShortName": "",
          "serviceId": "1_110802",
          "shapeId": "1_11010033",
          "timeZone": "",
          "tripHeadsign": "Capitol Hill Via 15th Ave E",
          "tripShortName": "LOCAL"
        },
        {
          "blockId": "1_4475924",
          "directionId": "1",
          "id": "1_33489763",
          "routeId": "1_100002",
          "routeShortName": "",
          "serviceId": "1_110802",
          "shapeId": "1_20010036",
          "timeZone": "",
          "tripHeadsign": "Downtown Seattle",
          "tripShortName": "LOCAL"
        },
        {
          "blockId": "1_4475929",
          "directionId": "0",
          "id": "1_33489871",
          "routeId": "1_100002",
          "routeShortName": "",
          "serviceId": "1_110802",
          "shapeId": "1_11010033",
          "timeZone": "",
          "tripHeadsign": "Capitol Hill Via 15th Ave E",
          "tripShortName": "LOCAL"
        },
        {
          "blockId": "1_4475929",
          "directionId": "0",
          "id": "1_33489869",
          "routeId": "1_100002",
          "routeShortName": "",
          "serviceId": "1_110802",
          "shapeId": "1_11010033",
          "timeZone": "",
          "tripHeadsign": "Capitol Hill Via 15th Ave E",
          "tripShortName": "LOCAL"
        }
      ]
    }
  },
  "text": "OK",
  "version": 2
}